{"title":"About Me","markdown":{"yaml":{"title":"About Me","format":"html"},"containsRefs":false,"markdown":"\n\nHi, I'm **Mirzokhidjon Yakubov**, a highly motivated and results-oriented Chief Specialist with extensive experience in international finance, central banking, and economic policy development. Over the course of my career, I have gained a comprehensive understanding of financial systems, regulatory compliance, and economic governance, with a strong track record of representing the Central Bank of Uzbekistan in engagements with leading international financial institutions, including the IMF, World Bank, and foreign central banks.  \n\nMy professional experience encompasses monitoring and evaluating the Bank’s compliance with international agreements, overseeing the accreditation and regulatory approval of foreign bank representative offices, and coordinating complex projects across multiple government agencies. I have been responsible for preparing detailed analytical reports, providing strategic policy recommendations, and supporting high-level decision-making processes that strengthen financial operations and ensure alignment with global standards.  \n\nBeyond technical expertise, I am passionate about leadership and capacity building. I have led cross-functional teams, mentored junior economists, and implemented initiatives that enhance operational efficiency, transparency, and organizational performance. My work is driven by a commitment to fostering collaboration, promoting best practices, and achieving measurable outcomes that support the sustainable growth of Uzbekistan’s financial sector.  \n\nIn addition to my central banking experience, I have also held leadership roles in the private sector, managing financial operations, budgeting, strategic planning, and personnel management. These experiences have enhanced my ability to navigate complex financial environments, make informed strategic decisions, and lead teams toward achieving organizational goals.  \n\nI am committed to continuous learning and professional development, staying informed on global economic trends, financial regulations, and emerging best practices. By combining technical expertise, leadership skills, and international experience, I aim to contribute meaningfully to financial governance, policy development, and organizational growth both in public institutions and the broader financial sector.\n\n\n\n\n","srcMarkdownNoYaml":"\n\nHi, I'm **Mirzokhidjon Yakubov**, a highly motivated and results-oriented Chief Specialist with extensive experience in international finance, central banking, and economic policy development. Over the course of my career, I have gained a comprehensive understanding of financial systems, regulatory compliance, and economic governance, with a strong track record of representing the Central Bank of Uzbekistan in engagements with leading international financial institutions, including the IMF, World Bank, and foreign central banks.  \n\nMy professional experience encompasses monitoring and evaluating the Bank’s compliance with international agreements, overseeing the accreditation and regulatory approval of foreign bank representative offices, and coordinating complex projects across multiple government agencies. I have been responsible for preparing detailed analytical reports, providing strategic policy recommendations, and supporting high-level decision-making processes that strengthen financial operations and ensure alignment with global standards.  \n\nBeyond technical expertise, I am passionate about leadership and capacity building. I have led cross-functional teams, mentored junior economists, and implemented initiatives that enhance operational efficiency, transparency, and organizational performance. My work is driven by a commitment to fostering collaboration, promoting best practices, and achieving measurable outcomes that support the sustainable growth of Uzbekistan’s financial sector.  \n\nIn addition to my central banking experience, I have also held leadership roles in the private sector, managing financial operations, budgeting, strategic planning, and personnel management. These experiences have enhanced my ability to navigate complex financial environments, make informed strategic decisions, and lead teams toward achieving organizational goals.  \n\nI am committed to continuous learning and professional development, staying informed on global economic trends, financial regulations, and emerging best practices. By combining technical expertise, leadership skills, and international experience, I aim to contribute meaningfully to financial governance, policy development, and organizational growth both in public institutions and the broader financial sector.\n\n\n\n\n"},"formats":{"html":{"identifier":{"display-name":"HTML","target-format":"html","base-format":"html"},"execute":{"fig-width":7,"fig-height":5,"fig-format":"retina","fig-dpi":96,"df-print":"default","error":false,"eval":true,"cache":null,"freeze":false,"echo":true,"output":true,"warning":true,"include":true,"keep-md":false,"keep-ipynb":false,"ipynb":null,"enabled":null,"daemon":null,"daemon-restart":false,"debug":false,"ipynb-filters":[],"ipynb-shell-interactivity":null,"plotly-connected":true,"engine":"markdown"},"render":{"keep-tex":false,"keep-typ":false,"keep-source":false,"keep-hidden":false,"prefer-html":false,"output-divs":true,"output-ext":"html","fig-align":"default","fig-pos":null,"fig-env":null,"code-fold":"none","code-overflow":"scroll","code-link":false,"code-line-numbers":false,"code-tools":false,"tbl-colwidths":"auto","merge-includes":true,"inline-includes":false,"preserve-yaml":false,"latex-auto-mk":true,"latex-auto-install":true,"latex-clean":true,"latex-min-runs":1,"latex-max-runs":10,"latex-makeindex":"makeindex","latex-makeindex-opts":[],"latex-tlmgr-opts":[],"latex-input-paths":[],"latex-output-dir":null,"link-external-icon":false,"link-external-newwindow":false,"self-contained-math":false,"format-resources":[],"notebook-links":true},"pandoc":{"standalone":true,"wrap":"none","default-image-extension":"png","to":"html","css":["styles.css"],"toc":true,"output-file":"about.html"},"language":{"toc-title-document":"Table of contents","toc-title-website":"On this page","related-formats-title":"Other Formats","related-notebooks-title":"Notebooks","source-notebooks-prefix":"Source","other-links-title":"Other Links","code-links-title":"Code Links","launch-dev-container-title":"Launch Dev Container","launch-binder-title":"Launch Binder","article-notebook-label":"Article Notebook","notebook-preview-download":"Download Notebook","notebook-preview-download-src":"Download Source","notebook-preview-back":"Back to Article","manuscript-meca-bundle":"MECA Bundle","section-title-abstract":"Abstract","section-title-appendices":"Appendices","section-title-footnotes":"Footnotes","section-title-references":"References","section-title-reuse":"Reuse","section-title-copyright":"Copyright","section-title-citation":"Citation","appendix-attribution-cite-as":"For attribution, please cite this work as:","appendix-attribution-bibtex":"BibTeX citation:","appendix-view-license":"View License","title-block-author-single":"Author","title-block-author-plural":"Authors","title-block-affiliation-single":"Affiliation","title-block-affiliation-plural":"Affiliations","title-block-published":"Published","title-block-modified":"Modified","title-block-keywords":"Keywords","callout-tip-title":"Tip","callout-note-title":"Note","callout-warning-title":"Warning","callout-important-title":"Important","callout-caution-title":"Caution","code-summary":"Code","code-tools-menu-caption":"Code","code-tools-show-all-code":"Show All Code","code-tools-hide-all-code":"Hide All Code","code-tools-view-source":"View Source","code-tools-source-code":"Source Code","tools-share":"Share","tools-download":"Download","code-line":"Line","code-lines":"Lines","copy-button-tooltip":"Copy to Clipboard","copy-button-tooltip-success":"Copied!","repo-action-links-edit":"Edit this page","repo-action-links-source":"View source","repo-action-links-issue":"Report an issue","back-to-top":"Back to top","search-no-results-text":"No results","search-matching-documents-text":"matching documents","search-copy-link-title":"Copy link to search","search-hide-matches-text":"Hide additional matches","search-more-match-text":"more match in this document","search-more-matches-text":"more matches in this document","search-clear-button-title":"Clear","search-text-placeholder":"","search-detached-cancel-button-title":"Cancel","search-submit-button-title":"Submit","search-label":"Search","toggle-section":"Toggle section","toggle-sidebar":"Toggle sidebar navigation","toggle-dark-mode":"Toggle dark mode","toggle-reader-mode":"Toggle reader mode","toggle-navigation":"Toggle navigation","crossref-fig-title":"Figure","crossref-tbl-title":"Table","crossref-lst-title":"Listing","crossref-thm-title":"Theorem","crossref-lem-title":"Lemma","crossref-cor-title":"Corollary","crossref-prp-title":"Proposition","crossref-cnj-title":"Conjecture","crossref-def-title":"Definition","crossref-exm-title":"Example","crossref-exr-title":"Exercise","crossref-ch-prefix":"Chapter","crossref-apx-prefix":"Appendix","crossref-sec-prefix":"Section","crossref-eq-prefix":"Equation","crossref-lof-title":"List of Figures","crossref-lot-title":"List of Tables","crossref-lol-title":"List of Listings","environment-proof-title":"Proof","environment-remark-title":"Remark","environment-solution-title":"Solution","listing-page-order-by":"Order By","listing-page-order-by-default":"Default","listing-page-order-by-date-asc":"Oldest","listing-page-order-by-date-desc":"Newest","listing-page-order-by-number-desc":"High to Low","listing-page-order-by-number-asc":"Low to High","listing-page-field-date":"Date","listing-page-field-title":"Title","listing-page-field-description":"Description","listing-page-field-author":"Author","listing-page-field-filename":"File Name","listing-page-field-filemodified":"Modified","listing-page-field-subtitle":"Subtitle","listing-page-field-readingtime":"Reading Time","listing-page-field-wordcount":"Word Count","listing-page-field-categories":"Categories","listing-page-minutes-compact":"{0} min","listing-page-category-all":"All","listing-page-no-matches":"No matching items","listing-page-words":"{0} words","listing-page-filter":"Filter","draft":"Draft"},"metadata":{"lang":"en","fig-responsive":true,"quarto-version":"1.7.32","theme":"cosmo","title":"About Me"},"extensions":{"book":{"multiFile":true}}}},"projectFormats":["html"]}